lunasynth/__init__.py
lunasynth/blender_addons/README.md
lunasynth/blender_addons/add_craters_blender_addon.py
lunasynth/blender_addons/add_rocks_blender_addon.py
lunasynth/blender_addons/add_sampling_cases_blender_addon.py
lunasynth/blender_helper.py
lunasynth/cli/README.md
lunasynth/cli/add_craters_mesh.py
lunasynth/cli/assign_pass_index.py
lunasynth/cli/combine_images.py
lunasynth/cli/create_crater_field.py
lunasynth/cli/create_multiview_video.py
lunasynth/cli/create_rock_field.py
lunasynth/cli/generate_enhanced_moon_terrain_dataset.py
lunasynth/cli/generate_traj_definition.py
lunasynth/cli/load_rocks.py
lunasynth/cli/mesh2blender.py
lunasynth/cli/process_sampling_cases.py
lunasynth/cli/process_traj_cases.py
lunasynth/cli/render_blendfile.py
lunasynth/cli/render_geotiff.py
lunasynth/cli/visualize_cases_blender.py
lunasynth/config_loader.py
lunasynth/configuration_manager.py
lunasynth/dem_tools.py
lunasynth/examples/README.md
lunasynth/examples/addon_example.py
lunasynth/examples/example_camera_pose.py
lunasynth/examples/example_random_camera.py
lunasynth/examples/example_sun_orientation.py
lunasynth/examples/example_sun_path_render.py
lunasynth/examples/view_exr_depth.py
lunasynth/examples/view_hdf_depth.py
lunasynth/examples/view_segmentation_image.py
lunasynth/generate_dummy_traj_landing.py
lunasynth/image_tools.py
lunasynth/terrain_enhancement.py
lunasynth-0.8.0.dist-info/LICENSE
lunasynth-0.8.0.dist-info/METADATA
lunasynth-0.8.0.dist-info/WHEEL
lunasynth-0.8.0.dist-info/entry_points.txt
lunasynth-0.8.0.dist-info/RECORD
