Metadata-Version: 2.1
Name: lunasynth
Version: 0.8.0
Summary: Generate synthetic lunar images using Blender
License: Apache-2.0
Author: Daniel Pastor
Author-email: daniel.pastor.moreno@jpl.nasa.gov
Requires-Python: ==3.11.10
Classifier: License :: OSI Approved :: Apache Software License
Classifier: Programming Language :: Python :: 3
Requires-Dist: argcomplete (>=3.3.0,<4.0.0)
Requires-Dist: bpy (>=4.1.0,<5.0.0)
Requires-Dist: bs4 (>=0.0.2,<0.0.3)
Requires-Dist: h5py (>=3.11.0,<4.0.0)
Requires-Dist: humanize (>=4.9.0,<5.0.0)
Requires-Dist: imageio (>=2.34.2,<3.0.0)
Requires-Dist: ipykernel (>=6.29.4,<7.0.0)
Requires-Dist: matplotlib (>=3.9.0,<4.0.0)
Requires-Dist: numba (>=0.60.0,<0.61.0)
Requires-Dist: numpy (>=1.26.4,<2.0.0)
Requires-Dist: opencv-python (>=4.9.0.80,<5.0.0.0)
Requires-Dist: opencv-python-headless (>=4.9.0.80,<5.0.0.0)
Requires-Dist: openexr (>=3.2.4,<4.0.0)
Requires-Dist: plotly (>=5.22.0,<6.0.0)
Requires-Dist: pyarrow (>=16.1.0,<17.0.0)
Requires-Dist: pyglet (<2)
Requires-Dist: rasterio (>=1.3.10,<2.0.0)
Requires-Dist: scipy (>=1.13.0,<2.0.0)
Requires-Dist: tabulate (>=0.9.0,<0.10.0)
Requires-Dist: trimesh (>=4.4.0,<5.0.0)
Requires-Dist: types-pyyaml (>=6.0.12.20240917,<7.0.0.0)
